custom_circle_plot/__init__.py
custom_circle_plot/example.py
custom_circle_plot/frontend/build/asset-manifest.json
custom_circle_plot/frontend/build/bootstrap.min.css
custom_circle_plot/frontend/build/bootstrap.min.css.map
custom_circle_plot/frontend/build/index.html
custom_circle_plot/frontend/build/static/css/main.8588038b.css
custom_circle_plot/frontend/build/static/css/main.8588038b.css.map
custom_circle_plot/frontend/build/static/js/main.1f50a459.js
custom_circle_plot/frontend/build/static/js/main.1f50a459.js.LICENSE.txt
custom_circle_plot/frontend/build/static/js/main.1f50a459.js.map
streamlit_circle_plot_component-0.0.5.dist-info/LICENSE
streamlit_circle_plot_component-0.0.5.dist-info/METADATA
streamlit_circle_plot_component-0.0.5.dist-info/WHEEL
streamlit_circle_plot_component-0.0.5.dist-info/top_level.txt
streamlit_circle_plot_component-0.0.5.dist-info/RECORD
